{
  "Black people politics Other/Global Zimbabwe to return land seized from foreign farmers::large2x": "https://images.pexels.com/photos/11196642/pexels-photo-11196642.jpeg?auto=compress&cs=tinysrgb&dpr=2&h=650&w=940",
  "hate crime Other/Global community people": "https://images.pexels.com/photos/8203490/pexels-photo-8203490.jpeg?auto=compress&cs=tinysrgb&h=650&w=940",
  "healthcare Other/Global community people": "https://images.pexels.com/photos/6646878/pexels-photo-6646878.jpeg?auto=compress&cs=tinysrgb&h=650&w=940",
  "employment Other/Global community people": "https://images.pexels.com/photos/12111234/pexels-photo-12111234.jpeg?auto=compress&cs=tinysrgb&h=650&w=940",
  "Black people Other/Global employment": "https://images.pexels.com/photos/5439381/pexels-photo-5439381.jpeg?auto=compress&cs=tinysrgb&h=650&w=940",
  "employment Africa community": "https://images.pexels.com/photos/11171617/pexels-photo-11171617.jpeg?auto=compress&cs=tinysrgb&h=650&w=940",
  "politics United States community people": "https://images.pexels.com/photos/1464200/pexels-photo-1464200.jpeg?auto=compress&cs=tinysrgb&h=650&w=940",
  "healthcare Ghana community people": "https://images.pexels.com/photos/35043641/pexels-photo-35043641.jpeg?auto=compress&cs=tinysrgb&h=650&w=940",
  "politics France community people": "https://images.pexels.com/photos/11421113/pexels-photo-11421113.jpeg?auto=compress&cs=tinysrgb&h=650&w=940",
  "policing United States community people": "https://images.pexels.com/photos/29549092/pexels-photo-29549092.jpeg?auto=compress&cs=tinysrgb&h=650&w=940",
  "Black people United States policing": "https://images.pexels.com/photos/29549092/pexels-photo-29549092.jpeg?auto=compress&cs=tinysrgb&h=650&w=940",
  "policing Africa community": "https://images.pexels.com/photos/5789288/pexels-photo-5789288.jpeg?auto=compress&cs=tinysrgb&h=650&w=940",
  "Black community policing": "https://images.pexels.com/photos/7714793/pexels-photo-7714793.jpeg?auto=compress&cs=tinysrgb&h=650&w=940",
  "education United States community people": "https://images.pexels.com/photos/396301/pexels-photo-396301.jpeg?auto=compress&cs=tinysrgb&h=650&w=940",
  "healthcare United States community people": "https://images.pexels.com/photos/6520106/pexels-photo-6520106.jpeg?auto=compress&cs=tinysrgb&h=650&w=940",
  "Black people United States healthcare": "https://images.pexels.com/photos/36770103/pexels-photo-36770103.jpeg?auto=compress&cs=tinysrgb&h=650&w=940",
  "healthcare Africa community": "https://images.pexels.com/photos/8248290/pexels-photo-8248290.jpeg?auto=compress&cs=tinysrgb&h=650&w=940",
  "Black community healthcare": "https://images.pexels.com/photos/6303652/pexels-photo-6303652.jpeg?auto=compress&cs=tinysrgb&h=650&w=940",
  "Black people United States education": "https://images.pexels.com/photos/10603626/pexels-photo-10603626.jpeg?auto=compress&cs=tinysrgb&h=650&w=940",
  "healthcare Canada community people": "https://images.pexels.com/photos/14797865/pexels-photo-14797865.jpeg?auto=compress&cs=tinysrgb&h=650&w=940",
  "politics Canada community people": "https://images.pexels.com/photos/11325547/pexels-photo-11325547.jpeg?auto=compress&cs=tinysrgb&h=650&w=940",
  "employment United States community people": "https://images.pexels.com/photos/4964772/pexels-photo-4964772.jpeg?auto=compress&cs=tinysrgb&h=650&w=940",
  "Black people United States employment": "https://images.pexels.com/photos/36153946/pexels-photo-36153946.jpeg?auto=compress&cs=tinysrgb&h=650&w=940",
  "Black community employment": "https://images.pexels.com/photos/6868263/pexels-photo-6868263.jpeg?auto=compress&cs=tinysrgb&h=650&w=940",
  "employment Canada community people": "https://images.pexels.com/photos/7221514/pexels-photo-7221514.jpeg?auto=compress&cs=tinysrgb&h=650&w=940",
  "policing Canada community people": "https://images.pexels.com/photos/5895409/pexels-photo-5895409.jpeg?auto=compress&cs=tinysrgb&h=650&w=940",
  "Black people United States politics": "https://images.pexels.com/photos/36793456/pexels-photo-36793456.jpeg?auto=compress&cs=tinysrgb&h=650&w=940",
  "demographics United States community people": "https://images.pexels.com/photos/1351720/pexels-photo-1351720.jpeg?auto=compress&cs=tinysrgb&h=650&w=940",
  "Black people Canada employment": "https://images.pexels.com/photos/8553862/pexels-photo-8553862.jpeg?auto=compress&cs=tinysrgb&h=650&w=940",
  "education Africa community": "https://images.pexels.com/photos/36188072/pexels-photo-36188072.jpeg?auto=compress&cs=tinysrgb&h=650&w=940",
  "Black community education": "https://images.pexels.com/photos/5905609/pexels-photo-5905609.jpeg?auto=compress&cs=tinysrgb&h=650&w=940",
  "hate crime United States community people": "https://images.pexels.com/photos/1464211/pexels-photo-1464211.jpeg?auto=compress&cs=tinysrgb&h=650&w=940",
  "politics Africa community": "https://images.pexels.com/photos/15993794/pexels-photo-15993794.jpeg?auto=compress&cs=tinysrgb&h=650&w=940",
  "Black people United States hate crime": "https://images.pexels.com/photos/1464211/pexels-photo-1464211.jpeg?auto=compress&cs=tinysrgb&h=650&w=940",
  "hate crime Africa community": "https://images.pexels.com/photos/8203490/pexels-photo-8203490.jpeg?auto=compress&cs=tinysrgb&h=650&w=940",
  "Black community hate crime": "https://images.pexels.com/photos/8203490/pexels-photo-8203490.jpeg?auto=compress&cs=tinysrgb&h=650&w=940",
  "housing United States community people": "https://images.pexels.com/photos/35246397/pexels-photo-35246397.jpeg?auto=compress&cs=tinysrgb&h=650&w=940",
  "Black people United States housing": "https://images.pexels.com/photos/30316627/pexels-photo-30316627.jpeg?auto=compress&cs=tinysrgb&h=650&w=940",
  "housing Africa community": "https://images.pexels.com/photos/32170343/pexels-photo-32170343.jpeg?auto=compress&cs=tinysrgb&h=650&w=940",
  "Black community housing": "https://images.pexels.com/photos/36709121/pexels-photo-36709121.jpeg?auto=compress&cs=tinysrgb&h=650&w=940",
  "Black people Canada healthcare": "https://images.pexels.com/photos/30677591/pexels-photo-30677591.jpeg?auto=compress&cs=tinysrgb&h=650&w=940",
  "other Canada community people": "https://images.pexels.com/photos/7221514/pexels-photo-7221514.jpeg?auto=compress&cs=tinysrgb&h=650&w=940",
  "Black people Canada other": "https://images.pexels.com/photos/6349487/pexels-photo-6349487.jpeg?auto=compress&cs=tinysrgb&h=650&w=940",
  "Black people Canada politics": "https://images.pexels.com/photos/11325547/pexels-photo-11325547.jpeg?auto=compress&cs=tinysrgb&h=650&w=940",
  "Black community politics": "https://images.pexels.com/photos/8847167/pexels-photo-8847167.jpeg?auto=compress&cs=tinysrgb&h=650&w=940",
  "Black people Canada policing": "https://images.pexels.com/photos/4626159/pexels-photo-4626159.jpeg?auto=compress&cs=tinysrgb&h=650&w=940",
  "other United States community people": "https://images.pexels.com/photos/8846266/pexels-photo-8846266.jpeg?auto=compress&cs=tinysrgb&h=650&w=940",
  "education Canada community people": "https://images.pexels.com/photos/18425136/pexels-photo-18425136.jpeg?auto=compress&cs=tinysrgb&h=650&w=940",
  "other Africa community": "https://images.pexels.com/photos/8042460/pexels-photo-8042460.jpeg?auto=compress&cs=tinysrgb&h=650&w=940",
  "Black community other": "https://images.pexels.com/photos/10617261/pexels-photo-10617261.jpeg?auto=compress&cs=tinysrgb&h=650&w=940",
  "Black people Canada education": "https://images.pexels.com/photos/6684602/pexels-photo-6684602.jpeg?auto=compress&cs=tinysrgb&h=650&w=940",
  "culture Canada community people": "https://images.pexels.com/photos/12449389/pexels-photo-12449389.jpeg?auto=compress&cs=tinysrgb&h=650&w=940",
  "Black people Canada culture": "https://images.pexels.com/photos/7220589/pexels-photo-7220589.jpeg?auto=compress&cs=tinysrgb&h=650&w=940",
  "hate crime Canada community people": "https://images.pexels.com/photos/8898655/pexels-photo-8898655.jpeg?auto=compress&cs=tinysrgb&h=650&w=940",
  "other Nigeria community people": "https://images.pexels.com/photos/8042460/pexels-photo-8042460.jpeg?auto=compress&cs=tinysrgb&h=650&w=940",
  "politics Other/Global community people": "https://images.pexels.com/photos/19894427/pexels-photo-19894427.jpeg?auto=compress&cs=tinysrgb&h=650&w=940",
  "Black people Other/Global politics": "https://images.pexels.com/photos/4570677/pexels-photo-4570677.jpeg?auto=compress&cs=tinysrgb&h=650&w=940",
  "other Other/Global community people": "https://images.pexels.com/photos/7475142/pexels-photo-7475142.jpeg?auto=compress&cs=tinysrgb&h=650&w=940",
  "Black people Other/Global other": "https://images.pexels.com/photos/7965690/pexels-photo-7965690.jpeg?auto=compress&cs=tinysrgb&h=650&w=940",
  "politics Nigeria community people": "https://images.pexels.com/photos/27555050/pexels-photo-27555050.jpeg?auto=compress&cs=tinysrgb&h=650&w=940",
  "politics Ghana community people": "https://images.pexels.com/photos/15993794/pexels-photo-15993794.jpeg?auto=compress&cs=tinysrgb&h=650&w=940",
  "Black people Ghana politics": "https://images.pexels.com/photos/19875800/pexels-photo-19875800.jpeg?auto=compress&cs=tinysrgb&h=650&w=940",
  "housing South Africa community people": "https://images.pexels.com/photos/3115325/pexels-photo-3115325.jpeg?auto=compress&cs=tinysrgb&h=650&w=940",
  "politics South Africa community people": "https://images.pexels.com/photos/11648153/pexels-photo-11648153.jpeg?auto=compress&cs=tinysrgb&h=650&w=940",
  "employment Nigeria community people": "https://images.pexels.com/photos/17916306/pexels-photo-17916306.jpeg?auto=compress&cs=tinysrgb&h=650&w=940",
  "Black people Nigeria politics": "https://images.pexels.com/photos/27555050/pexels-photo-27555050.jpeg?auto=compress&cs=tinysrgb&h=650&w=940",
  "Black people Nigeria employment": "https://images.pexels.com/photos/30688591/pexels-photo-30688591.jpeg?auto=compress&cs=tinysrgb&h=650&w=940",
  "employment South Africa community people": "https://images.pexels.com/photos/12491632/pexels-photo-12491632.jpeg?auto=compress&cs=tinysrgb&h=650&w=940",
  "Black people Other/Global hate crime": "https://images.pexels.com/photos/8203490/pexels-photo-8203490.jpeg?auto=compress&cs=tinysrgb&h=650&w=940",
  "Black people Other/Global healthcare": "https://images.pexels.com/photos/4302197/pexels-photo-4302197.jpeg?auto=compress&cs=tinysrgb&h=650&w=940",
  "housing Other/Global community people": "https://images.pexels.com/photos/8805579/pexels-photo-8805579.jpeg?auto=compress&cs=tinysrgb&h=650&w=940",
  "Black people Other/Global housing": "https://images.pexels.com/photos/10505742/pexels-photo-10505742.jpeg?auto=compress&cs=tinysrgb&h=650&w=940",
  "Black people South Africa employment": "https://images.pexels.com/photos/955388/pexels-photo-955388.jpeg?auto=compress&cs=tinysrgb&h=650&w=940",
  "economy Ghana community people": "https://images.pexels.com/photos/36392321/pexels-photo-36392321.jpeg?auto=compress&cs=tinysrgb&h=650&w=940",
  "economy Nigeria community people": "https://images.pexels.com/photos/2282803/pexels-photo-2282803.jpeg?auto=compress&cs=tinysrgb&h=650&w=940",
  "Black people South Africa politics": "https://images.pexels.com/photos/10527763/pexels-photo-10527763.jpeg?auto=compress&cs=tinysrgb&h=650&w=940",
  "healthcare South Africa community people": "https://images.pexels.com/photos/10807180/pexels-photo-10807180.jpeg?auto=compress&cs=tinysrgb&h=650&w=940",
  "education Nigeria community people": "https://images.pexels.com/photos/33976359/pexels-photo-33976359.jpeg?auto=compress&cs=tinysrgb&h=650&w=940",
  "Black people South Africa housing": "https://images.pexels.com/photos/3115325/pexels-photo-3115325.jpeg?auto=compress&cs=tinysrgb&h=650&w=940",
  "education Other/Global community people": "https://images.pexels.com/photos/32099426/pexels-photo-32099426.jpeg?auto=compress&cs=tinysrgb&h=650&w=940",
  "culture Other/Global community people": "https://images.pexels.com/photos/8770950/pexels-photo-8770950.jpeg?auto=compress&cs=tinysrgb&h=650&w=940",
  "healthcare United Kingdom community people": "https://images.pexels.com/photos/16509486/pexels-photo-16509486.jpeg?auto=compress&cs=tinysrgb&h=650&w=940",
  "Black people United Kingdom healthcare": "https://images.pexels.com/photos/10603626/pexels-photo-10603626.jpeg?auto=compress&cs=tinysrgb&h=650&w=940",
  "housing United Kingdom community people": "https://images.pexels.com/photos/15993255/pexels-photo-15993255.jpeg?auto=compress&cs=tinysrgb&h=650&w=940",
  "hate crime Brazil community people": "https://images.pexels.com/photos/14357047/pexels-photo-14357047.jpeg?auto=compress&cs=tinysrgb&h=650&w=940",
  "education United Kingdom community people": "https://images.pexels.com/photos/7156129/pexels-photo-7156129.jpeg?auto=compress&cs=tinysrgb&h=650&w=940",
  "culture United Kingdom community people": "https://images.pexels.com/photos/36766054/pexels-photo-36766054.jpeg?auto=compress&cs=tinysrgb&h=650&w=940"
}